{
    "key": "group_62e176ac6b859",
    "title": "CPT - Artist",
    "fields": [],
    "location": [
        [
            {
                "param": "post_type",
                "operator": "==",
                "value": "artist"
            }
        ]
    ],
    "menu_order": 0,
    "position": "normal",
    "style": "default",
    "label_placement": "top",
    "instruction_placement": "label",
    "hide_on_screen": "",
    "active": true,
    "description": "",
    "show_in_rest": 0,
    "modified": 1658943168
}